tictoc/__init__.py
tictoc/tictoc.py
matlab_tictoc-1.3.0.dist-info/LICENSE
matlab_tictoc-1.3.0.dist-info/METADATA
matlab_tictoc-1.3.0.dist-info/WHEEL
matlab_tictoc-1.3.0.dist-info/top_level.txt
matlab_tictoc-1.3.0.dist-info/RECORD
