Metadata-Version: 2.1
Name: matlab-tictoc
Version: 1.3.0
Summary: A timing package that mimics MATLAB's tic and toc functionality
Author: Matthew Altberg
Requires-Python: >=3.7
License-File: LICENSE
